{"IdElement":"promo","Width":0,"Height":0,"Header":"Уникальность","Slides":[{"ImgSource":"promo\\promoe3699318-61a0-42d3-a05a-63ee32a39787.png","AltText":"документ","Width":150,"Height":150,"HeaderText":"Диагностика странностей","RegularText":"Улучшим, и будет класс"},{"ImgSource":"promo\\promoa50c1698-f153-423b-88e3-3054d387bc09.png","AltText":"hyrth","Width":150,"Height":150,"HeaderText":"Рихтовка цилиндров","RegularText":"Супер инфа"},{"ImgSource":"promo\\promo3eb61219-6ccc-4f71-b9b4-a96f7b22c6ec.png","AltText":"trhrthrth","Width":150,"Height":150,"HeaderText":"Мощность мотора","RegularText":"Офигеть вообще"}]}